taposockets/__init__.py
taposockets/__main__.py
taposockets/cipher.py
taposockets/cli.py
taposockets/status_code.py
taposockets-1.2.0.dist-info/METADATA
taposockets-1.2.0.dist-info/WHEEL
taposockets-1.2.0.dist-info/top_level.txt
taposockets-1.2.0.dist-info/RECORD
