Metadata-Version: 2.1
Name: taposockets
Version: 1.2.0
Summary: A Python library for Tapo sockets.
Home-page: https://github.com/iamatulsingh/taposockets
Author: Atul Singh
Author-email: atulsingh0401@gmail.com
Classifier: Programming Language :: Python :: 3
Classifier: License :: OSI Approved :: MIT License
Classifier: Operating System :: OS Independent
Requires-Python: >=3.8
Requires-Dist: pkcs7 (==0.1.2)
Requires-Dist: pycryptodome (==3.16.0)
Requires-Dist: requests (==2.27.1)
Requires-Dist: python-dotenv (==0.21.0)
Requires-Dist: pre-commit (==2.21.0)
Requires-Dist: pytest (==7.2.0)
